traq/__init__.py
traq/api_client.py
traq/configuration.py
traq/exceptions.py
traq/model_utils.py
traq/rest.py
traq/api/__init__.py
traq/api/activity_api.py
traq/api/authentication_api.py
traq/api/bot_api.py
traq/api/channel_api.py
traq/api/clip_api.py
traq/api/file_api.py
traq/api/group_api.py
traq/api/me_api.py
traq/api/message_api.py
traq/api/notification_api.py
traq/api/oauth2_api.py
traq/api/ogp_api.py
traq/api/pin_api.py
traq/api/public_api.py
traq/api/stamp_api.py
traq/api/star_api.py
traq/api/user_api.py
traq/api/user_tag_api.py
traq/api/webhook_api.py
traq/api/webrtc_api.py
traq/apis/__init__.py
traq/model/__init__.py
traq/model/active_o_auth2_token.py
traq/model/activity_timeline_message.py
traq/model/bot.py
traq/model/bot_detail.py
traq/model/bot_event_log.py
traq/model/bot_event_result.py
traq/model/bot_mode.py
traq/model/bot_state.py
traq/model/bot_tokens.py
traq/model/bot_user.py
traq/model/channel.py
traq/model/channel_event.py
traq/model/channel_list.py
traq/model/channel_stats.py
traq/model/channel_stats_stamp.py
traq/model/channel_stats_user.py
traq/model/channel_subscribe_level.py
traq/model/channel_topic.py
traq/model/channel_view_state.py
traq/model/channel_viewer.py
traq/model/child_created_event.py
traq/model/clip_folder.py
traq/model/clipped_message.py
traq/model/dm_channel.py
traq/model/external_provider_user.py
traq/model/file_info.py
traq/model/file_info_thumbnail.py
traq/model/forced_notification_changed_event.py
traq/model/get_notify_citation.py
traq/model/login_session.py
traq/model/message.py
traq/model/message_clip.py
traq/model/message_pin.py
traq/model/message_search_result.py
traq/model/message_stamp.py
traq/model/my_channel_view_state.py
traq/model/my_user_detail.py
traq/model/name_changed_event.py
traq/model/o_auth2_client.py
traq/model/o_auth2_client_detail.py
traq/model/o_auth2_prompt.py
traq/model/o_auth2_response_type.py
traq/model/o_auth2_scope.py
traq/model/o_auth2_token.py
traq/model/ogp.py
traq/model/ogp_media.py
traq-3.9.1.post0.dist-info/METADATA
traq-3.9.1.post0.dist-info/WHEEL
traq-3.9.1.post0.dist-info/top_level.txt
traq-3.9.1.post0.dist-info/RECORD
